[
  {"word":"diligent","category":"General"},{"word":"meticulous","category":"General"},
  {"word":"ample","category":"General"},{"word":"cordial","category":"General"},
  {"word":"deft","category":"General"},{"word":"eloquent","category":"General"},
  {"word":"feasible","category":"General"},{"word":"gregarious","category":"General"},
  {"word":"hapless","category":"General"},{"word":"impartial","category":"General"},
  {"word":"jubilant","category":"General"},{"word":"lucid","category":"General"},
  {"word":"mundane","category":"General"},{"word":"notorious","category":"General"},
  {"word":"obstinate","category":"General"},{"word":"pragmatic","category":"General"},
  {"word":"quaint","category":"General"},{"word":"resilient","category":"General"},
  {"word":"sturdy","category":"General"},{"word":"tedious","category":"General"},
  {"word":"unanimous","category":"General"},{"word":"vivid","category":"General"},
  {"word":"wary","category":"General"},{"word":"zealous","category":"General"},
  {"word":"benevolent","category":"General"},{"word":"candor","category":"General"},
  {"word":"diligence","category":"General"},{"word":"endeavor","category":"General"},
  {"word":"fortitude","category":"General"},{"word":"humility","category":"General"},
  {"word":"abundant","category":"General"},{"word":"authentic","category":"General"},
  {"word":"bewilder","category":"General"},{"word":"candid","category":"General"},
  {"word":"compassion","category":"General"},{"word":"conceal","category":"General"},
  {"word":"concur","category":"General"},{"word":"deceive","category":"General"},
  {"word":"despair","category":"General"},{"word":"empathy","category":"General"},
  {"word":"enormous","category":"General"},{"word":"fascinate","category":"General"},
  {"word":"genuine","category":"General"},{"word":"hostile","category":"General"},
  {"word":"imitate","category":"General"},{"word":"leisure","category":"General"},
  {"word":"marvel","category":"General"},{"word":"naive","category":"General"},
  {"word":"optimistic","category":"General"},{"word":"pessimistic","category":"General"},
  {"word":"profound","category":"General"},{"word":"reluctant","category":"General"},
  {"word":"sincere","category":"General"},{"word":"thrive","category":"General"},
  {"word":"versatile","category":"General"},{"word":"yearn","category":"General"},
  {"word":"alienate","category":"General"},{"word":"allege","category":"General"},
  {"word":"allocate","category":"General"},{"word":"amateur","category":"General"},
  {"word":"ambition","category":"General"},{"word":"ancestor","category":"General"},
  {"word":"anticipate","category":"General"},{"word":"appetite","category":"General"},
  {"word":"approximate","category":"General"},{"word":"artificial","category":"General"},
  {"word":"ascend","category":"General"},{"word":"aspire","category":"General"},
  {"word":"astonish","category":"General"},{"word":"attain","category":"General"},
  {"word":"attribute","category":"General"},

  {"word":"abate","category":"SSC"},{"word":"abscond","category":"SSC"},
  {"word":"acquit","category":"SSC"},{"word":"adhere","category":"SSC"},
  {"word":"alleviate","category":"SSC"},{"word":"ambiguous","category":"SSC"},
  {"word":"appease","category":"SSC"},{"word":"arbitrary","category":"SSC"},
  {"word":"austere","category":"SSC"},{"word":"belligerent","category":"SSC"},
  {"word":"connive","category":"SSC"},{"word":"coerce","category":"SSC"},
  {"word":"condone","category":"SSC"},{"word":"contentious","category":"SSC"},
  {"word":"cursory","category":"SSC"},{"word":"deprecate","category":"SSC"},
  {"word":"discern","category":"SSC"},{"word":"dismantle","category":"SSC"},
  {"word":"elicit","category":"SSC"},{"word":"exonerate","category":"SSC"},
  {"word":"fervent","category":"SSC"},{"word":"garrulous","category":"SSC"},
  {"word":"hamper","category":"SSC"},{"word":"impede","category":"SSC"},
  {"word":"incite","category":"SSC"},{"word":"indignant","category":"SSC"},
  {"word":"inevitable","category":"SSC"},{"word":"mitigate","category":"SSC"},
  {"word":"obsolete","category":"SSC"},{"word":"plausible","category":"SSC"},
  {"word":"abdicate","category":"SSC"},{"word":"abhor","category":"SSC"},
  {"word":"amalgamate","category":"SSC"},{"word":"anarchy","category":"SSC"},
  {"word":"apathy","category":"SSC"},{"word":"audacious","category":"SSC"},
  {"word":"barren","category":"SSC"},{"word":"boisterous","category":"SSC"},
  {"word":"callous","category":"SSC"},{"word":"capitulate","category":"SSC"},
  {"word":"chastise","category":"SSC"},{"word":"clandestine","category":"SSC"},
  {"word":"cynical","category":"SSC"},{"word":"defiance","category":"SSC"},
  {"word":"derogatory","category":"SSC"},{"word":"dexterous","category":"SSC"},
  {"word":"emulate","category":"SSC"},{"word":"enigmatic","category":"SSC"},
  {"word":"evade","category":"SSC"},{"word":"exorbitant","category":"SSC"},
  {"word":"fabricate","category":"SSC"},{"word":"frivolous","category":"SSC"},
  {"word":"frugal","category":"SSC"},{"word":"gullible","category":"SSC"},
  {"word":"hypocrite","category":"SSC"},{"word":"illicit","category":"SSC"},
  {"word":"impetuous","category":"SSC"},{"word":"indolent","category":"SSC"},
  {"word":"insolent","category":"SSC"},{"word":"lethargic","category":"SSC"},
  {"word":"lucrative","category":"SSC"},{"word":"morose","category":"SSC"},
  {"word":"novice","category":"SSC"},{"word":"oblivious","category":"SSC"},
  {"word":"ostentatious","category":"SSC"},{"word":"penchant","category":"SSC"},
  {"word":"placate","category":"SSC"},{"word":"prodigal","category":"SSC"},
  {"word":"repudiate","category":"SSC"},{"word":"reticent","category":"SSC"},
  {"word":"sporadic","category":"SSC"},{"word":"sycophant","category":"SSC"},
  {"word":"treacherous","category":"SSC"},{"word":"venerate","category":"SSC"},

  {"word":"abstruse","category":"GRE"},{"word":"acumen","category":"GRE"},
  {"word":"alacrity","category":"GRE"},{"word":"anomaly","category":"GRE"},
  {"word":"antipathy","category":"GRE"},{"word":"cacophony","category":"GRE"},
  {"word":"capricious","category":"GRE"},{"word":"chicanery","category":"GRE"},
  {"word":"conflagration","category":"GRE"},{"word":"ephemeral","category":"GRE"},
  {"word":"equanimity","category":"GRE"},{"word":"esoteric","category":"GRE"},
  {"word":"fastidious","category":"GRE"},{"word":"iconoclast","category":"GRE"},
  {"word":"inchoate","category":"GRE"},{"word":"laconic","category":"GRE"},
  {"word":"magnanimous","category":"GRE"},{"word":"obfuscate","category":"GRE"},
  {"word":"parsimonious","category":"GRE"},{"word":"perfunctory","category":"GRE"},
  {"word":"pernicious","category":"GRE"},{"word":"philistine","category":"GRE"},
  {"word":"quixotic","category":"GRE"},{"word":"recalcitrant","category":"GRE"},
  {"word":"sanguine","category":"GRE"},{"word":"taciturn","category":"GRE"},
  {"word":"ubiquitous","category":"GRE"},{"word":"vicissitude","category":"GRE"},
  {"word":"winsome","category":"GRE"},{"word":"zealot","category":"GRE"},
  {"word":"aberration","category":"GRE"},{"word":"anachronism","category":"GRE"},
  {"word":"burgeoning","category":"GRE"},{"word":"castigate","category":"GRE"},
  {"word":"catalyst","category":"GRE"},{"word":"caustic","category":"GRE"},
  {"word":"cogent","category":"GRE"},{"word":"commensurate","category":"GRE"},
  {"word":"compendium","category":"GRE"},{"word":"complaisant","category":"GRE"},
  {"word":"craven","category":"GRE"},{"word":"decorum","category":"GRE"},
  {"word":"desiccate","category":"GRE"},{"word":"diatribe","category":"GRE"},
  {"word":"didactic","category":"GRE"},{"word":"dirge","category":"GRE"},
  {"word":"disabuse","category":"GRE"},{"word":"disparate","category":"GRE"},
  {"word":"dogmatic","category":"GRE"},{"word":"eclectic","category":"GRE"},
  {"word":"efficacy","category":"GRE"},{"word":"elegy","category":"GRE"},
  {"word":"enervate","category":"GRE"},{"word":"engender","category":"GRE"},
  {"word":"equivocate","category":"GRE"},{"word":"erudite","category":"GRE"},
  {"word":"eulogy","category":"GRE"},{"word":"foment","category":"GRE"},
  {"word":"gainsay","category":"GRE"},{"word":"guile","category":"GRE"},
  {"word":"homogenous","category":"GRE"},{"word":"iconoclastic","category":"GRE"},
  {"word":"imperturbable","category":"GRE"},{"word":"implacable","category":"GRE"},
  {"word":"insipid","category":"GRE"},{"word":"intransigent","category":"GRE"},
  {"word":"irascible","category":"GRE"},{"word":"loquacious","category":"GRE"},
  {"word":"misanthrope","category":"GRE"},{"word":"obdurate","category":"GRE"},
  {"word":"obsequious","category":"GRE"},{"word":"pedantic","category":"GRE"},
  {"word":"precipitate","category":"GRE"},{"word":"prevaricate","category":"GRE"},
  {"word":"propitiate","category":"GRE"},{"word":"specious","category":"GRE"},
  {"word":"vituperative","category":"GRE"},{"word":"volatile","category":"GRE"},

  {"word":"abrogate","category":"UPSC"},{"word":"accede","category":"UPSC"},
  {"word":"acrimony","category":"UPSC"},{"word":"ameliorate","category":"UPSC"},
  {"word":"austerity","category":"UPSC"},{"word":"bureaucracy","category":"UPSC"},
  {"word":"centralize","category":"UPSC"},{"word":"coalition","category":"UPSC"},
  {"word":"conundrum","category":"UPSC"},{"word":"disparity","category":"UPSC"},
  {"word":"devolution","category":"UPSC"},{"word":"egalitarian","category":"UPSC"},
  {"word":"emancipate","category":"UPSC"},{"word":"exigency","category":"UPSC"},
  {"word":"hegemony","category":"UPSC"},{"word":"imperative","category":"UPSC"},
  {"word":"incumbent","category":"UPSC"},{"word":"insurgency","category":"UPSC"},
  {"word":"jurisdiction","category":"UPSC"},{"word":"legislate","category":"UPSC"},
  {"word":"mandate","category":"UPSC"},{"word":"nepotism","category":"UPSC"},
  {"word":"oligarchy","category":"UPSC"},{"word":"plebiscite","category":"UPSC"},
  {"word":"populism","category":"UPSC"},{"word":"precedent","category":"UPSC"},
  {"word":"referendum","category":"UPSC"},{"word":"sovereignty","category":"UPSC"},
  {"word":"statute","category":"UPSC"},{"word":"xenophobia","category":"UPSC"},
  {"word":"accountability","category":"UPSC"},{"word":"adjudicate","category":"UPSC"},
  {"word":"agrarian","category":"UPSC"},{"word":"amendment","category":"UPSC"},
  {"word":"amnesty","category":"UPSC"},{"word":"autonomy","category":"UPSC"},
  {"word":"bicameral","category":"UPSC"},{"word":"capitalism","category":"UPSC"},
  {"word":"chauvinism","category":"UPSC"},{"word":"communism","category":"UPSC"},
  {"word":"consensus","category":"UPSC"},{"word":"demography","category":"UPSC"},
  {"word":"diplomacy","category":"UPSC"},{"word":"enfranchise","category":"UPSC"},
  {"word":"espionage","category":"UPSC"},{"word":"federalism","category":"UPSC"},
  {"word":"filibuster","category":"UPSC"},{"word":"globalization","category":"UPSC"},
  {"word":"imperialism","category":"UPSC"},{"word":"indictment","category":"UPSC"},
  {"word":"judiciary","category":"UPSC"},{"word":"marginalize","category":"UPSC"},
  {"word":"moratorium","category":"UPSC"},{"word":"nationalism","category":"UPSC"},
  {"word":"ordinance","category":"UPSC"},{"word":"pluralism","category":"UPSC"},
  {"word":"prerogative","category":"UPSC"},{"word":"ratify","category":"UPSC"},
  {"word":"republicanism","category":"UPSC"},{"word":"secularism","category":"UPSC"},
  {"word":"socialism","category":"UPSC"},{"word":"subversion","category":"UPSC"},
  {"word":"totalitarian","category":"UPSC"},{"word":"tribunal","category":"UPSC"},
  {"word":"unilateral","category":"UPSC"},

  {"word":"acerbic","category":"CAT"},{"word":"adroit","category":"CAT"},
  {"word":"apocryphal","category":"CAT"},{"word":"arcane","category":"CAT"},
  {"word":"ascetic","category":"CAT"},{"word":"banal","category":"CAT"},
  {"word":"bucolic","category":"CAT"},{"word":"calumny","category":"CAT"},
  {"word":"chasm","category":"CAT"},{"word":"circumscribe","category":"CAT"},
  {"word":"convoluted","category":"CAT"},{"word":"dearth","category":"CAT"},
  {"word":"debilitate","category":"CAT"},{"word":"demagogue","category":"CAT"},
  {"word":"deride","category":"CAT"},{"word":"diffident","category":"CAT"},
  {"word":"ebullient","category":"CAT"},{"word":"egregious","category":"CAT"},
  {"word":"exacerbate","category":"CAT"},{"word":"fatuous","category":"CAT"},
  {"word":"hackneyed","category":"CAT"},{"word":"harangue","category":"CAT"},
  {"word":"idiosyncrasy","category":"CAT"},{"word":"ineffable","category":"CAT"},
  {"word":"insidious","category":"CAT"},{"word":"juxtapose","category":"CAT"},
  {"word":"lugubrious","category":"CAT"},{"word":"mendacious","category":"CAT"},
  {"word":"munificent","category":"CAT"},{"word":"paragon","category":"CAT"},
  {"word":"polemical","category":"CAT"},{"word":"proclivity","category":"CAT"},
  {"word":"pugnacious","category":"CAT"},{"word":"aggregate","category":"CAT"},
  {"word":"arbitrage","category":"CAT"},{"word":"consolidate","category":"CAT"},
  {"word":"discrepancy","category":"CAT"},{"word":"equilibrium","category":"CAT"},
  {"word":"extrapolate","category":"CAT"},{"word":"leverage","category":"CAT"},
  {"word":"paradigm","category":"CAT"},{"word":"synthesis","category":"CAT"},

  {"word":"acquisition","category":"IELTS"},{"word":"compatible","category":"IELTS"},
  {"word":"comprehensive","category":"IELTS"},{"word":"consequence","category":"IELTS"},
  {"word":"detrimental","category":"IELTS"},{"word":"devastating","category":"IELTS"},
  {"word":"dimension","category":"IELTS"},{"word":"fluctuate","category":"IELTS"},
  {"word":"hypothesis","category":"IELTS"},{"word":"implication","category":"IELTS"},
  {"word":"inherent","category":"IELTS"},{"word":"innovative","category":"IELTS"},
  {"word":"insight","category":"IELTS"},{"word":"integrate","category":"IELTS"},
  {"word":"interpret","category":"IELTS"},{"word":"methodology","category":"IELTS"},
  {"word":"perspective","category":"IELTS"},{"word":"phenomenon","category":"IELTS"},
  {"word":"proponent","category":"IELTS"},{"word":"proportion","category":"IELTS"},
  {"word":"substantial","category":"IELTS"},{"word":"theoretical","category":"IELTS"},
  {"word":"validity","category":"IELTS"},{"word":"coherent","category":"IELTS"},
  {"word":"contemporary","category":"IELTS"},{"word":"controversial","category":"IELTS"},
  {"word":"conventional","category":"IELTS"},{"word":"empirical","category":"IELTS"},
  {"word":"implicit","category":"IELTS"},{"word":"prevalent","category":"IELTS"},

  {"word":"amortize","category":"Bank"},{"word":"annuity","category":"Bank"},
  {"word":"appraisal","category":"Bank"},{"word":"arrears","category":"Bank"},
  {"word":"audit","category":"Bank"},{"word":"bearish","category":"Bank"},
  {"word":"bullish","category":"Bank"},{"word":"collateral","category":"Bank"},
  {"word":"commodity","category":"Bank"},{"word":"compliance","category":"Bank"},
  {"word":"creditor","category":"Bank"},{"word":"default","category":"Bank"},
  {"word":"deflation","category":"Bank"},{"word":"depreciation","category":"Bank"},
  {"word":"derivative","category":"Bank"},{"word":"disbursement","category":"Bank"},
  {"word":"dividend","category":"Bank"},{"word":"escrow","category":"Bank"},
  {"word":"expenditure","category":"Bank"},{"word":"fiduciary","category":"Bank"},
  {"word":"fiscal","category":"Bank"},{"word":"foreclosure","category":"Bank"},
  {"word":"franchise","category":"Bank"},{"word":"guarantor","category":"Bank"},
  {"word":"inflation","category":"Bank"},{"word":"insolvency","category":"Bank"},
  {"word":"liquidation","category":"Bank"},{"word":"liquidity","category":"Bank"},
  {"word":"macroeconomics","category":"Bank"},{"word":"marginal","category":"Bank"},
  {"word":"monetary","category":"Bank"},{"word":"mortgage","category":"Bank"},
  {"word":"mutual","category":"Bank"},{"word":"nominal","category":"Bank"},
  {"word":"overdraft","category":"Bank"},{"word":"portfolio","category":"Bank"},
  {"word":"prospectus","category":"Bank"},{"word":"recession","category":"Bank"},
  {"word":"remittance","category":"Bank"},{"word":"securities","category":"Bank"},
  {"word":"stagnant","category":"Bank"},{"word":"subsidy","category":"Bank"},
  {"word":"surplus","category":"Bank"},{"word":"tariff","category":"Bank"},
  {"word":"treasury","category":"Bank"},{"word":"yield","category":"Bank"},
  {"word":"solvency","category":"Bank"},

  {"word":"abolish","category":"State_PCS"},{"word":"affidavit","category":"State_PCS"},
  {"word":"allegation","category":"State_PCS"},{"word":"amend","category":"State_PCS"},
  {"word":"appellate","category":"State_PCS"},{"word":"autocrat","category":"State_PCS"},
  {"word":"charter","category":"State_PCS"},{"word":"cite","category":"State_PCS"},
  {"word":"civilian","category":"State_PCS"},{"word":"commission","category":"State_PCS"},
  {"word":"decree","category":"State_PCS"},{"word":"delegate","category":"State_PCS"},
  {"word":"directive","category":"State_PCS"},{"word":"doctrine","category":"State_PCS"},
  {"word":"domicile","category":"State_PCS"},{"word":"electorate","category":"State_PCS"},
  {"word":"enact","category":"State_PCS"},{"word":"gazette","category":"State_PCS"},
  {"word":"governance","category":"State_PCS"},{"word":"hierarchy","category":"State_PCS"},
  {"word":"impeach","category":"State_PCS"},{"word":"infrastructure","category":"State_PCS"},
  {"word":"jurisprudence","category":"State_PCS"},{"word":"legislature","category":"State_PCS"},
  {"word":"magistrate","category":"State_PCS"},{"word":"manifesto","category":"State_PCS"},
  {"word":"panchayat","category":"State_PCS"},{"word":"protocol","category":"State_PCS"},
  {"word":"quorum","category":"State_PCS"},{"word":"secular","category":"State_PCS"},
  {"word":"tenure","category":"State_PCS"},{"word":"veto","category":"State_PCS"},
  {"word":"bureaucratic","category":"State_PCS"},{"word":"decentralize","category":"State_PCS"},
  {"word":"delimitation","category":"State_PCS"},{"word":"deprived","category":"State_PCS"},
  {"word":"grievance","category":"State_PCS"},{"word":"indigenous","category":"State_PCS"},
  {"word":"rehabilitation","category":"State_PCS"},{"word":"welfare","category":"State_PCS"}
]